flytekitplugins_deck_standard-1.16.12-py3.14-nspkg.pth
flytekitplugins/deck/__init__.py
flytekitplugins/deck/renderer.py
flytekitplugins_deck_standard-1.16.12.dist-info/METADATA
flytekitplugins_deck_standard-1.16.12.dist-info/WHEEL
flytekitplugins_deck_standard-1.16.12.dist-info/entry_points.txt
flytekitplugins_deck_standard-1.16.12.dist-info/namespace_packages.txt
flytekitplugins_deck_standard-1.16.12.dist-info/top_level.txt
flytekitplugins_deck_standard-1.16.12.dist-info/RECORD
