Metadata-Version: 2.4
Name: flytekitplugins-deck-standard
Version: 1.16.12
Summary: This Plugin provides more renderers to improve task visibility
Home-page: https://github.com/flyteorg/flytekit/tree/master/plugins/flytekit-data-fsspec
Author: flyteorg
Author-email: admin@flyte.org
License: apache2
Classifier: Intended Audience :: Science/Research
Classifier: Intended Audience :: Developers
Classifier: License :: OSI Approved :: Apache Software License
Classifier: Programming Language :: Python :: 3.9
Classifier: Programming Language :: Python :: 3.10
Classifier: Programming Language :: Python :: 3.11
Classifier: Programming Language :: Python :: 3.12
Classifier: Topic :: Scientific/Engineering
Classifier: Topic :: Scientific/Engineering :: Artificial Intelligence
Classifier: Topic :: Software Development
Classifier: Topic :: Software Development :: Libraries
Classifier: Topic :: Software Development :: Libraries :: Python Modules
Requires-Python: >=3.9
Requires-Dist: flytekit
Provides-Extra: pandas
Requires-Dist: pandas; extra == "pandas"
Provides-Extra: pillow
Requires-Dist: pillow; extra == "pillow"
Provides-Extra: ydata-profiling
Requires-Dist: ydata-profiling; extra == "ydata-profiling"
Provides-Extra: markdown
Requires-Dist: markdown; extra == "markdown"
Provides-Extra: plotly
Requires-Dist: plotly; extra == "plotly"
Provides-Extra: pygments
Requires-Dist: pygments; extra == "pygments"
Provides-Extra: all
Requires-Dist: pandas<=2.2.3; python_version < "3.10" and extra == "all"
Requires-Dist: pandas; python_version > "3.9" and extra == "all"
Requires-Dist: pillow; extra == "all"
Requires-Dist: ydata-profiling; extra == "all"
Requires-Dist: markdown; extra == "all"
Requires-Dist: plotly; extra == "all"
Requires-Dist: pygments; extra == "all"
Dynamic: author
Dynamic: author-email
Dynamic: classifier
Dynamic: description
Dynamic: description-content-type
Dynamic: home-page
Dynamic: license
Dynamic: provides-extra
Dynamic: requires-dist
Dynamic: requires-python
Dynamic: summary
